orc_dev_cli/__init__.py
orc_dev_cli/addon_state.py
orc_dev_cli/cli.py
orc_dev_cli/cluster/__init__.py
orc_dev_cli/cluster/cli.py
orc_dev_cli/cluster/defaults.py
orc_dev_cli/cluster/delete.py
orc_dev_cli/cluster/list.py
orc_dev_cli/cluster/login.py
orc_dev_cli/cluster/status.py
orc_dev_cli/code.py
orc_dev_cli/config.py
orc_dev_cli/data/index_build.toml
orc_dev_cli/helper.py
orc_dev_cli/rhoam/__init__.py
orc_dev_cli/rhoam/cli.py
orc_dev_cli/rhoam/delete.py
orc_dev_cli/rhoam/index/__init__.py
orc_dev_cli/rhoam/index/default.py
orc_dev_cli/rhoam/status.py
orc_dev_cli-0.7.1.dist-info/METADATA
orc_dev_cli-0.7.1.dist-info/WHEEL
orc_dev_cli-0.7.1.dist-info/entry_points.txt
orc_dev_cli-0.7.1.dist-info/RECORD
