Metadata-Version: 2.1
Name: orc-dev-cli
Version: 0.7.1
Summary: CLI dev tool for interacting with openshift clusters and RHOAM addons.
Home-page: https://github.com/Boomatang/orc-dev-cli
Keywords: OpenShift,addon,operator,index,bundle
Author: Jim Fitzpatrick
Author-email: jimfity@gmail.com
Requires-Python: >=3.10,<4.0
Classifier: Intended Audience :: Developers
Classifier: Programming Language :: Python :: 3
Classifier: Programming Language :: Python :: 3.10
Classifier: Programming Language :: Python :: 3.11
Classifier: Topic :: Software Development :: Build Tools
Requires-Dist: GitPython (>=3.1.28,<4.0.0)
Requires-Dist: PyYAML (>=6.0,<7.0)
Requires-Dist: click (>=8.1.2,<9.0.0)
Requires-Dist: podman (>=4.2.0,<5.0.0)
Requires-Dist: pydantic (>=1.10.4,<2.0.0)
Requires-Dist: pyperclip (>=1.8.2,<2.0.0)
Requires-Dist: requests (>=2.28.1,<3.0.0)
Requires-Dist: rich (>=13.2.0,<14.0.0)
Requires-Dist: semver (>=2.13.0,<3.0.0)
Requires-Dist: toml (>=0.10.2,<0.11.0) ; python_version < "3.11"
Project-URL: Documentation, https://github.com/Boomatang/orc-dev-cli/tree/main/doc
Project-URL: Repository, https://github.com/Boomatang/orc-dev-cli
